tornado_rest_easy/__init__.py
tornado_rest_easy/_version.py
tornado_rest_easy/handler.py
tornado_rest_easy/path.py
tornado_rest_easy/tree.py
tornado_rest_easy/utils.py
tornado_rest_easy-0.1.dist-info/LICENSE
tornado_rest_easy-0.1.dist-info/METADATA
tornado_rest_easy-0.1.dist-info/WHEEL
tornado_rest_easy-0.1.dist-info/top_level.txt
tornado_rest_easy-0.1.dist-info/RECORD
