Metadata-Version: 2.1
Name: tornado-rest-easy
Version: 0.1
Summary: library for easy restful APIs in tornado
Home-page: https://github.com/postelrich/tornado-restful
Author: Richard Postelnik
Author-email: richard.postelnik@gmail.com
License: UNKNOWN
Platform: UNKNOWN
Classifier: Programming Language :: Python :: 3
Classifier: License :: OSI Approved :: BSD License
Classifier: Operating System :: OS Independent
Requires-Dist: tornado
